AUTHORS.md
CONTRIBUTING.md
HISTORY.md
README.md
regexp_learner/__init__.py
regexp_learner/gold/__init__.py
regexp_learner/gold/gold.py
regexp_learner/gold/observation_table.py
regexp_learner/lstar/__init__.py
regexp_learner/lstar/automaton_match.py
regexp_learner/lstar/learner.py
regexp_learner/lstar/observation_table.py
regexp_learner/lstar/teacher.py
regexp_learner/strings.py
regexp_learner-1.0.2.dist-info/WHEEL
regexp_learner-1.0.2.dist-info/METADATA
regexp_learner-1.0.2.dist-info/LICENSE
regexp_learner-1.0.2.dist-info/RECORD
