Metadata-Version: 2.1
Name: regexp-learner
Version: 1.0.2
Summary: Python3 module providing some algorithms to infer automata and regular expressions.
License: BSD-3 license
Author: Marc-Olivier Buob
Author-email: marc-olivier.buob@nokia-bell-labs.com
Requires-Python: >=3.10,<4.0
Classifier: License :: Other/Proprietary License
Classifier: Programming Language :: Python :: 3
Classifier: Programming Language :: Python :: 3.10
Classifier: Programming Language :: Python :: 3.11
Requires-Dist: ipython (>=8.10.0)
Requires-Dist: numpy (>=2.2.6)
Requires-Dist: pybgl (>=0.11.1)
